feature_flags/__init__.py
feature_flags/admin.py
feature_flags/apps.py
feature_flags/models.py
feature_flags/tests.py
feature_flags/utils.py
feature_flags/views.py
feature_flags/migrations/__init__.py
django_feature_flags-0.0.3.dist-info/LICENCE
django_feature_flags-0.0.3.dist-info/LICENSE
django_feature_flags-0.0.3.dist-info/METADATA
django_feature_flags-0.0.3.dist-info/WHEEL
django_feature_flags-0.0.3.dist-info/top_level.txt
django_feature_flags-0.0.3.dist-info/RECORD
