Metadata-Version: 2.1
Name: django-feature-flags
Version: 0.0.3
Summary: A django app to help you manage the django-shopify-app package billing
Home-page: http://pypi.python.org/pypi/django-feature-flags/
Author: 
Author-email: 
License: MIT
License-File: LICENCE
License-File: LICENSE
Requires-Dist: Django
